<?xml version="1.0" encoding="UTF-8"?>
<GenRun Id="impl_1" LaunchPart="xc7a35tcpg236-1" LaunchTime="1763652978">
  <File Type="PA-TCL" Name="step1.tcl"/>
  <File Type="REPORTS-TCL" Name="step1_reports.tcl"/>
  <File Type="INIT-TIMING" Name="step1_timing_summary_init.rpt"/>
  <File Type="OPT-DCP" Name="step1_opt.dcp"/>
  <File Type="OPT-DRC" Name="step1_drc_opted.rpt"/>
  <File Type="OPT-UTIL" Name="step1_utilization_opted.rpt"/>
  <File Type="OPT-UTIL-PB" Name="step1_utilization_opted.pb"/>
  <File Type="OPT-METHODOLOGY-DRC" Name="step1_methodology_drc_opted.rpt"/>
  <File Type="OPT-HWDEF" Name="step1.hwdef"/>
  <File Type="OPT-TIMING" Name="step1_timing_summary_opted.rpt"/>
  <File Type="OPT-RQA-PB" Name="step1_rqa_opted.pb"/>
  <File Type="PWROPT-DCP" Name="step1_pwropt.dcp"/>
  <File Type="PWROPT-DRC" Name="step1_drc_pwropted.rpt"/>
  <File Type="PWROPT-TIMING" Name="step1_timing_summary_pwropted.rpt"/>
  <File Type="PLACE-DCP" Name="step1_placed.dcp"/>
  <File Type="PLACE-IO" Name="step1_io_placed.rpt"/>
  <File Type="PLACE-CLK" Name="step1_clock_utilization_placed.rpt"/>
  <File Type="PLACE-UTIL" Name="step1_utilization_placed.rpt"/>
  <File Type="PLACE-UTIL-PB" Name="step1_utilization_placed.pb"/>
  <File Type="PLACE-CTRL" Name="step1_control_sets_placed.rpt"/>
  <File Type="PLACE-SIMILARITY" Name="step1_incremental_reuse_placed.rpt"/>
  <File Type="PLACE-PRE-SIMILARITY" Name="step1_incremental_reuse_pre_placed.rpt"/>
  <File Type="PLACE-TIMING" Name="step1_timing_summary_placed.rpt"/>
  <File Type="PLACE-RQA-PB" Name="step1_rqa_placed.pb"/>
  <File Type="POSTPLACE-PWROPT-DCP" Name="step1_postplace_pwropt.dcp"/>
  <File Type="POSTPLACE-PWROPT-TIMING" Name="step1_timing_summary_postplace_pwropted.rpt"/>
  <File Type="PHYSOPT-DCP" Name="step1_physopt.dcp"/>
  <File Type="PHYSOPT-DRC" Name="step1_drc_physopted.rpt"/>
  <File Type="PHYSOPT-TIMING" Name="step1_timing_summary_physopted.rpt"/>
  <File Type="ROUTE-ERROR-DCP" Name="step1_routed_error.dcp"/>
  <File Type="ROUTE-DCP" Name="step1_routed.dcp"/>
  <File Type="ROUTE-BLACKBOX-DCP" Name="step1_routed_bb.dcp"/>
  <File Type="ROUTE-UTIL" Name="step1_utilization_routed.rpt"/>
  <File Type="ROUTE-UTIL-PB" Name="step1_utilization_routed.pb"/>
  <File Type="ROUTE-DRC" Name="step1_drc_routed.rpt"/>
  <File Type="ROUTE-DRC-PB" Name="step1_drc_routed.pb"/>
  <File Type="ROUTE-DRC-RPX" Name="step1_drc_routed.rpx"/>
  <File Type="ROUTE-METHODOLOGY-DRC" Name="step1_methodology_drc_routed.rpt"/>
  <File Type="ROUTE-METHODOLOGY-DRC-RPX" Name="step1_methodology_drc_routed.rpx"/>
  <File Type="ROUTE-METHODOLOGY-DRC-PB" Name="step1_methodology_drc_routed.pb"/>
  <File Type="ROUTE-PWR" Name="step1_power_routed.rpt"/>
  <File Type="ROUTE-PWR-SUM" Name="step1_power_summary_routed.pb"/>
  <File Type="ROUTE-PWR-RPX" Name="step1_power_routed.rpx"/>
  <File Type="ROUTE-STATUS" Name="step1_route_status.rpt"/>
  <File Type="ROUTE-STATUS-PB" Name="step1_route_status.pb"/>
  <File Type="ROUTE-TIMINGSUMMARY" Name="step1_timing_summary_routed.rpt"/>
  <File Type="ROUTE-TIMING-PB" Name="step1_timing_summary_routed.pb"/>
  <File Type="ROUTE-TIMING-RPX" Name="step1_timing_summary_routed.rpx"/>
  <File Type="ROUTE-SIMILARITY" Name="step1_incremental_reuse_routed.rpt"/>
  <File Type="ROUTE-CLK" Name="step1_clock_utilization_routed.rpt"/>
  <File Type="ROUTE-BUS-SKEW" Name="step1_bus_skew_routed.rpt"/>
  <File Type="ROUTE-BUS-SKEW-PB" Name="step1_bus_skew_routed.pb"/>
  <File Type="ROUTE-BUS-SKEW-RPX" Name="step1_bus_skew_routed.rpx"/>
  <File Type="ROUTE-RQS-PB" Name="step1_rqs_routed.pb"/>
  <File Type="POSTROUTE-PHYSOPT-DCP" Name="step1_postroute_physopt.dcp"/>
  <File Type="POSTROUTE-PHYSOPT-BLACKBOX-DCP" Name="step1_postroute_physopt_bb.dcp"/>
  <File Type="POSTROUTE-PHYSOPT-TIMING" Name="step1_timing_summary_postroute_physopted.rpt"/>
  <File Type="POSTROUTE-PHYSOPT-TIMING-PB" Name="step1_timing_summary_postroute_physopted.pb"/>
  <File Type="POSTROUTE-PHYSOPT-TIMING-RPX" Name="step1_timing_summary_postroute_physopted.rpx"/>
  <File Type="POSTROUTE-PHYSOPT-BUS-SKEW" Name="step1_bus_skew_postroute_physopted.rpt"/>
  <File Type="POSTROUTE-PHYSOPT-BUS-SKEW-PB" Name="step1_bus_skew_postroute_physopted.pb"/>
  <File Type="POSTROUTE-PHYSOPT-BUS-SKEW-RPX" Name="step1_bus_skew_postroute_physopted.rpx"/>
  <File Type="BG-BIT" Name="step1.bit"/>
  <File Type="BG-BIN" Name="step1.bin"/>
  <File Type="BITSTR-MSK" Name="step1.msk"/>
  <File Type="BITSTR-RBT" Name="step1.rbt"/>
  <File Type="BITSTR-NKY" Name="step1.nky"/>
  <File Type="BITSTR-BMM" Name="step1_bd.bmm"/>
  <File Type="BITSTR-MMI" Name="step1.mmi"/>
  <File Type="PDI-FILE" Name="step1.pdi"/>
  <File Type="BOOT-PDI-FILE" Name="step1_boot.pdi"/>
  <File Type="PL-PDI-FILE" Name="step1_pld.pdi"/>
  <File Type="RCFI_FILE" Name="step1.rcfi"/>
  <File Type="CFI_FILE" Name="step1.cfi"/>
  <File Type="RNPI_FILE" Name="step1.rnpi"/>
  <File Type="RCDO-FILE" Name="step1.rcdo"/>
  <File Type="MARKER-RNPI-FILE" Name="step1_markers.rnpi"/>
  <File Type="MARKER-RCDO-FILE" Name="step1_markers.rcdo"/>
  <File Type="BOOT_RNPI_FILE" Name="step1_boot.rnpi"/>
  <File Type="BOOT_MARKER_RNPI_FILE" Name="step1_boot_markers.rnpi"/>
  <File Type="PL_RNPI_FILE" Name="step1_pld.rnpi"/>
  <File Type="PL_MARKER_RNPI_FILE" Name="step1_pld_markers.rnpi"/>
  <File Type="PL_MASK_RNPI_FILE" Name="step1_pld_mask.rnpi"/>
  <File Type="PL_SHUTDOWN_RNPI_FILE" Name="step1_pld_shutdown.rnpi"/>
  <File Type="PL_UNMASK_RNPI_FILE" Name="step1_pld_unmask.rnpi"/>
  <File Type="PL-RCDO-FILE" Name="step1_pld.rcdo"/>
  <File Type="PL-CLEAR-RCDO-FILE" Name="step1_pld_clear.rcdo"/>
  <File Type="PL_MARKER_RCDO_FILE" Name="step1_pld_markers.rcdo"/>
  <File Type="PL_MASK_RCDO_FILE" Name="step1_pld_mask.rcdo"/>
  <File Type="PL_UNMASK_MARKER_RCDO_FILE" Name="step1_pld_unmask_markers.rcdo"/>
  <File Type="PL_UNMASK_RCDO_FILE" Name="step1_pld_unmask.rcdo"/>
  <File Type="NPI_FILE" Name="step1.npi"/>
  <File Type="RBD_FILE" Name="step1.rbd"/>
  <File Type="MMI-FILE" Name="step1.mmi"/>
  <File Type="BIF-FILE" Name="step1.bif"/>
  <File Type="BOOT-BIF-FILE" Name="step1_boot.bif"/>
  <File Type="PL-BIF-FILE" Name="step1_pld.bif"/>
  <File Type="LTX-FILE" Name="step1.ltx"/>
  <File Type="BOOT-LTX-FILE" Name="step1_boot.ltx"/>
  <File Type="PL-LTX-FILE" Name="step1_pld.ltx"/>
  <File Type="BITSTR-LTX" Name="debug_nets.ltx"/>
  <File Type="BITSTR-LTX" Name="step1.ltx"/>
  <File Type="BITSTR-SYSDEF" Name="step1.sysdef"/>
  <File Type="BG-BGN" Name="step1.bgn"/>
  <File Type="BG-DRC" Name="step1.drc"/>
  <File Type="RDI-RDI" Name="step1.vdi"/>
  <File Type="WBT-USG" Name="usage_statistics_webtalk.html"/>
  <File Type="ROUTE-RQS" Name="step1_routed.rqs"/>
  <File Type="POSTROUTE-PHYSOPT-RQS" Name="step1_postroute_physopted.rqs"/>
  <File Type="ROUTE-RQS-RPT" Name="route_report_qor_suggestions_0.rpt"/>
  <File Type="POSTROUTE-PHYSOPT-RQS-RPT" Name="postroute_physopt_report_qor_suggestions_0.rpt"/>
  <FileSet Name="sources" Type="DesignSrcs" RelSrcDir="$PSRCDIR/sources_1" RelGenDir="$PGENDIR/sources_1">
    <Filter Type="Srcs"/>
    <File Path="$PSRCDIR/sources_1/new/dependencies.v">
      <FileInfo>
        <Attr Name="UsedIn" Val="synthesis"/>
        <Attr Name="UsedIn" Val="implementation"/>
        <Attr Name="UsedIn" Val="simulation"/>
      </FileInfo>
    </File>
    <File Path="$PSRCDIR/sources_1/new/step1.v">
      <FileInfo>
        <Attr Name="UsedIn" Val="synthesis"/>
        <Attr Name="UsedIn" Val="implementation"/>
        <Attr Name="UsedIn" Val="simulation"/>
      </FileInfo>
    </File>
    <File Path="$PSRCDIR/sources_1/new/top.v">
      <FileInfo>
        <Attr Name="UserDisabled" Val="1"/>
        <Attr Name="UsedIn" Val="synthesis"/>
        <Attr Name="UsedIn" Val="implementation"/>
        <Attr Name="UsedIn" Val="simulation"/>
      </FileInfo>
    </File>
    <Config>
      <Option Name="DesignMode" Val="RTL"/>
      <Option Name="TopModule" Val="step1"/>
    </Config>
  </FileSet>
  <FileSet Name="constrs_in" Type="Constrs" RelSrcDir="$PSRCDIR/constrs_1" RelGenDir="$PGENDIR/constrs_1">
    <Filter Type="Constrs"/>
    <File Path="$PSRCDIR/constrs_1/imports/Vivado work/Basys-3-Mastercopy.xdc">
      <FileInfo>
        <Attr Name="ImportPath" Val="$PPRDIR/../../../../var/home/david/Documents/Vivado work/Basys-3-Mastercopy.xdc"/>
        <Attr Name="ImportTime" Val="1763479856"/>
        <Attr Name="UsedIn" Val="synthesis"/>
        <Attr Name="UsedIn" Val="implementation"/>
      </FileInfo>
    </File>
    <Config>
      <Option Name="ConstrsType" Val="XDC"/>
    </Config>
  </FileSet>
  <FileSet Name="utils" Type="Utils" RelSrcDir="$PSRCDIR/utils_1" RelGenDir="$PGENDIR/utils_1">
    <Filter Type="Utils"/>
    <File Path="$PSRCDIR/utils_1/imports/synth_1/top.dcp">
      <FileInfo>
        <Attr Name="UsedIn" Val="synthesis"/>
        <Attr Name="UsedIn" Val="implementation"/>
        <Attr Name="UsedInSteps" Val="synth_1"/>
        <Attr Name="AutoDcp" Val="1"/>
      </FileInfo>
    </File>
    <Config>
      <Option Name="TopAutoSet" Val="TRUE"/>
    </Config>
  </FileSet>
  <Strategy Version="1" Minor="2">
    <StratHandle Name="Vivado Implementation Defaults" Flow="Vivado Implementation 2025"/>
    <Step Id="init_design"/>
    <Step Id="opt_design"/>
    <Step Id="power_opt_design"/>
    <Step Id="place_design"/>
    <Step Id="post_place_power_opt_design"/>
    <Step Id="phys_opt_design"/>
    <Step Id="route_design"/>
    <Step Id="post_route_phys_opt_design"/>
    <Step Id="write_bitstream"/>
  </Strategy>
</GenRun>
